{
    "department": "자유전공학부",
    "curriculum": [
      {
        "year": 1,
        "semester": 1,
        "courses": [
          {
            "type": "교필",
            "name": "세종인을위한진로설계",
            "credits": 1
          },
          {
            "type": "교필",
            "name": "서양철학:쟁점과토론",
            "credits": 3
          },
          {
            "type": "교필",
            "name": "대학영어",
            "credits": 2
          },
          {
            "type": "교선",
            "name": "새잎창의세미나",
            "credits": 3
          },
          {
            "type": "교선(희망)",
            "name": "미적분학입문",
            "credits": 3
          },
          {
            "type": "교선(희망)",
            "name": "통계학입문",
            "credits": 3
          },
          {
            "type": "교선(희망)",
            "name": "물리학입문",
            "credits": 3
          },
          {
            "type": "학기",
            "name": "미적분학1",
            "credits": 3
          },
          {
            "type": "전기",
            "name": "일반물리학1",
            "credits": 3
          },
          {
            "type": "전기",
            "name": "일반화학1",
            "credits": 3
          },
          {
            "type": "전기",
            "name": "일반생물학1",
            "credits": 3
          }
        ]
      },
      {
        "year": 1,
        "semester": 2,
        "courses": [
          {
            "type": "교필",
            "name": "세종인을위한전공탐색",
            "credits": 1
          },
          {
            "type": "교필",
            "name": "문제해결을위한글쓰기와발표",
            "credits": 3
          },
          {
            "type": "교필",
            "name": "우주자연인간",
            "credits": 1
          },
          {
            "type": "교선",
            "name": "새잎융합세미나",
            "credits": 3
          },
          {
            "type": "학기",
            "name": "SW기초코딩",
            "credits": 3
          },
          {
            "type": "전기(A)",
            "name": "기초통계학",
            "credits": 3
          },
          {
            "type": "전기(A)",
            "name": "기초천문학",
            "credits": 3
          },
          {
            "type": "전기(A)",
            "name": "기초생물통계학",
            "credits": 3
          },
          {
            "type": "전기(A)",
            "name": "미적분학2",
            "credits": 3
          },
          {
            "type": "전기(A)",
            "name": "일반물리학2",
            "credits": 3
          },
          {
            "type": "전기(A)",
            "name": "일반화학2",
            "credits": 3
          },
          {
            "type": "전기(A)",
            "name": "일반생물학2",
            "credits": 3
          }
        ]
      },
      {
        "year": 2,
        "semester": 1,
        "courses": [
            {    
               "type": "학기",
               "name": "인공지능과빅데이터",
               "credits": 3
            }
        ]
      }
    ]
}